elastic/pipes/core/__init__.py
elastic/pipes/core/errors.py
elastic/pipes/core/export.py
elastic/pipes/core/import.py
elastic/pipes/core/kibana.py
elastic/pipes/core/runner.py
elastic/pipes/core/shelllib.py
elastic/pipes/core/standalone.py
elastic/pipes/core/util.py
elastic/pipes/hcp/vault/common.py
elastic/pipes/hcp/vault/read.py
elastic/pipes/hcp/vault/write.py
elastic_pipes-0.7.0.dist-info/LICENSE.txt
elastic_pipes-0.7.0.dist-info/METADATA
elastic_pipes-0.7.0.dist-info/WHEEL
elastic_pipes-0.7.0.dist-info/entry_points.txt
elastic_pipes-0.7.0.dist-info/top_level.txt
elastic_pipes-0.7.0.dist-info/RECORD
