Metadata-Version: 2.1
Name: elastic-pipes
Version: 0.7.0
Summary: A lightweight composition system
Author-email: Domenico Andreoli <domenico.andreoli@elastic.co>
License: Apache-2.0
Project-URL: Homepage, https://github.com/elastic/pipes-py
Project-URL: Bug Tracker, https://github.com/elastic/pipes-py/issues
Classifier: License :: OSI Approved :: Apache Software License
Classifier: Programming Language :: Python
Classifier: Topic :: Software Development :: Libraries :: Python Modules
Requires-Python: >=3.8
License-File: LICENSE.txt
Requires-Dist: elasticsearch >=8.2.0
Requires-Dist: hvac >=2.0.0
Requires-Dist: pyyaml
Requires-Dist: requests
Requires-Dist: semver
Requires-Dist: typer
Requires-Dist: typing-extensions >=4.12.0
